README.md
setup.py
image_to_numpy/__init__.py
image_to_numpy/src.py
image_to_numpy.egg-info/PKG-INFO
image_to_numpy.egg-info/SOURCES.txt
image_to_numpy.egg-info/dependency_links.txt
image_to_numpy.egg-info/requires.txt
image_to_numpy.egg-info/top_level.txt