Metadata-Version: 2.1
Name: image-to-numpy
Version: 1.0.0
Summary: Load an image into a numpy array with proper Exif orientation handling
Home-page: https://github.com/ageitgey/image_to_numpy
Author: Adam Geitgey
Author-email: ageitgey@gmail.com
License: MIT
Platform: UNKNOWN
Classifier: License :: OSI Approved :: MIT License
Classifier: Programming Language :: Python
Classifier: Programming Language :: Python :: 3
